hexin_server/__init__.py
hexin_server/__main__.py
hexin_server-0.1.23.dist-info/METADATA
hexin_server-0.1.23.dist-info/WHEEL
hexin_server-0.1.23.dist-info/entry_points.txt
hexin_server-0.1.23.dist-info/licenses/LICENSE
hexin_server-0.1.23.dist-info/RECORD
